{
  "name": "prove-map",
  "handlers": [
    {
      "on": "select",
      "target": "runtime",
      "domain": "prove",
      "action": "fire-shapes",
      "args": {
        "component": "map"
      },
      "returns": {
        "ok": "boolean",
        "total": "number",
        "passed": "number"
      }
    },
    {
      "on": "marker:click",
      "target": "runtime",
      "domain": "prove",
      "action": "fire-shapes",
      "args": {
        "component": "map"
      },
      "returns": {
        "ok": "boolean",
        "total": "number",
        "passed": "number"
      }
    }
  ]
}
